block_fragments/__init__.py
block_fragments/apps.py
block_fragments/exceptions.py
block_fragments/loader.py
block_fragments/template.py
django_block_fragments-0.1.1.dist-info/METADATA
django_block_fragments-0.1.1.dist-info/WHEEL
django_block_fragments-0.1.1.dist-info/licenses/LICENSE
django_block_fragments-0.1.1.dist-info/RECORD
