Metadata-Version: 2.4
Name: django-block-fragments
Version: 0.1.1
Summary: Reusable block fragments for the Django Template Language.
Author-email: Kai Schlamp <kai.schlamp@gmail.com>
License-File: LICENSE
Requires-Python: >=3.10
Requires-Dist: django>=5.0.0
